mkdocs_graphviz.py
mkdocs_graphviz-1.5.3.dist-info/LICENSE
mkdocs_graphviz-1.5.3.dist-info/METADATA
mkdocs_graphviz-1.5.3.dist-info/WHEEL
mkdocs_graphviz-1.5.3.dist-info/top_level.txt
mkdocs_graphviz-1.5.3.dist-info/RECORD
